renameit/__init__.py
renameit/cli.py
renameit_cli-0.1.2.dist-info/METADATA
renameit_cli-0.1.2.dist-info/WHEEL
renameit_cli-0.1.2.dist-info/entry_points.txt
renameit_cli-0.1.2.dist-info/top_level.txt
renameit_cli-0.1.2.dist-info/RECORD
