Metadata-Version: 2.4
Name: renameit-cli
Version: 0.1.2
Summary: Simple CLI tool to rename files and folders
Author-email: "M.Ammar Ali" <m.ammarali.910@gmail.com>
License-Expression: MIT
Requires-Python: >=3.8
